README.md
setup.py
color_print/__init__.py
simple_color_print.egg-info/PKG-INFO
simple_color_print.egg-info/SOURCES.txt
simple_color_print.egg-info/dependency_links.txt
simple_color_print.egg-info/top_level.txt