Metadata-Version: 1.2
Name: simple-color-print
Version: 0.2.8
Summary: Simple color print
Home-page: https://github.com/bzdvdn/simple-color-print
Author: bzdvdn
Author-email: bzdv.dn@gmail.com
License: MIT
Platform: UNKNOWN
Requires-Python: >=3.6
